{
  "titles": ["TENME BRILLANDO"],
  "authors": ["Autor desconocido"],
  "languages": ["spanish"],
  "songbooks": [{ "name": "Nuestos Himnos Predilectos", "number": "176" }],
  "lyrics": [
    {
      "language": "spanish",
      "order": ["v1", "c1", "v2", "c1", "v3", "c2"],
      "v1": [
        "Tenme brillando, Señor, tenme brillando por Ti~",
        "Puro y limpio seré, si Tú brillas en mí.",
        "Será mi vida, Señor, cual un lucero por Ti,",
        "hasta que vengas con tu gran poder."
      ],
      "c1": [
        "Oh, llévame a la gloria salvado por Ti.",
        "Llévame, Señor, quiero estar allí.",
        "Oh, llévame a tu gloria salvado por Ti.",
        "Sólo allí tu Rostro veré."
      ],
      "v2": [
        "Dame tu ayuda, Señor, para que brille por Ti.",
        "Yo andaré en tu amor, si Tú brillas en mí.",
        "Seme propicio, Señor, quiero alumbrar en redor,",
        "hasta que vengas con tu gran poder."
      ],
      "v3": [
        "Quiero ser tuyo, Señor, siempre alumbrando",
        "por Ti. Lucharé con valor, si Tú brillas en mí.",
        "En Ti confío, Señor, para luchar con valor,",
        "hasta que vengas con tu gran poder ."
      ],
      "c2": [
        "Oh, llévame a la roca más alta que yo,",
        "llévame, Señor, yo te seguiré.",
        "Oh, llévame a la roca más alta que yo,",
        "sólo allí refugio tendré."
      ]
    }
  ],
  "versions": []
}
