{
  "titles": ["Que Hermosas Son"],
  "authors": ["Autor Desconocido"],
  "songbooks": [{ "name": "Himnario de coros", "number": "198" }],
  "languages": ["spanish"],
  "versions": [],
  "lyrics": [
    {
      "language": "spanish",
      "order": ["v1", "v2"],
      "lyric": {
        "v1": [
          "/: Qué hermosas son las horas",
          "que pasa el cristiano",
          "Postrado en la tierra"
        ],
        "v2": [
          "en ferviente oración:/",
          "/: Pidiendo ser lleno del Espíritu Santo",
          "y ser mensajero de todo Poder:/"
        ]
      }
    }
  ]
}
