<?xml version="1.0" encoding="UTF-8"?><song xmlns="http://openlyrics.info/namespace/2009/song" version="0.8" createdIn="toOpenLyrics"><properties><titles><title lang="es">Me Haz Tomado</title></titles><auhtors><auhtor>Autor Desconocido</auhtor></auhtors><songbooks><songbook entry="13" name="Himnario de coros"/></songbooks><verseOrder>v1 v2 v3 v4 v5</verseOrder></properties><lyrics><verse name="v1" lang="es"><lines>Al estar en la presencia de tu Divinidad</lines><lines>al contemplar la hermosura de tu santidad.</lines><lines>Mi espíritu se alegra en tu Majestad</lines></verse><verse name="v2" lang="es"><lines>/:te adoro a Ti:/</lines><lines>Cuando veo la grandeza de tu dulce amor</lines><lines>y compruebo la pureza de tu corazón.</lines></verse><verse name="v3" lang="es"><lines>Mi espíritu se alegra en tu Majestad</lines><lines>/:te adoro a Ti:/</lines><lines>Y al estar aquí delante de Ti, te adoraré</lines></verse><verse name="v4" lang="es"><lines>postrado ante Ti mi corazón te adora oh Dios</lines><lines>y siempre quiero estar para adorar</lines><lines>y contemplar tu santidad</lines></verse><verse name="v5" lang="es"><lines>/: Te adoro a Ti, Señor, te adoro a Ti:/</lines></verse></lyrics></song>