<?xml version="1.0" encoding="UTF-8"?><song xmlns="http://openlyrics.info/namespace/2009/song" version="0.8" createdIn="toOpenLyrics"><properties><titles><title lang="es">Yo Quiero Ser Un Vaso</title></titles><auhtors><auhtor>Autor Desconocido</auhtor></auhtors><songbooks><songbook entry="94" name="Himnario de coros"/></songbooks><verseOrder>v1 v2 v3 v4 v5</verseOrder></properties><lyrics><verse name="v1" lang="es"><lines>/: Yo quiero ser un vaso</lines><lines>para honra del Señor: /</lines><lines>Señor llena mi vaso</lines></verse><verse name="v2" lang="es"><lines>con tu Espíritu Santo</lines><lines>yo quiero ser un vaso</lines><lines>para honra del Señor.</lines></verse><verse name="v3" lang="es"><lines>/: Lléname, lléname,</lines><lines>lléname con tu Poder: /</lines><lines>Lleno quiero ser Señor</lines></verse><verse name="v4" lang="es"><lines>Y en tu viña trabajar</lines><lines>lléname, lléname,</lines><lines>lléname con tu Poder. (Úsame...</lines></verse><verse name="v5" lang="es"><lines>Bautízame.  ..)</lines></verse></lyrics></song>