<?xml version="1.0" encoding="UTF-8"?><song xmlns="http://openlyrics.info/namespace/2009/song" version="0.8" createdIn="toOpenLyrics"><properties><titles><title lang="es">Gracias Te Doy</title></titles><auhtors><auhtor>Autor Desconocido</auhtor></auhtors><songbooks><songbook entry="5" name="Himnario de coros"/></songbooks><verseOrder>v1 v2</verseOrder></properties><lyrics><verse name="v1" lang="es"><lines>/: Gracias te doy Señor: /</lines><lines>en este día gracias te doy.</lines><lines>/: Que por mis culpas</lines></verse><verse name="v2" lang="es"><lines>y mis pecados</lines><lines>diste tu vida, oh buen Señor: /.</lines></verse></lyrics></song>