<?xml version="1.0" encoding="UTF-8"?><song xmlns="http://openlyrics.info/namespace/2009/song" version="0.8" createdIn="toOpenLyrics"><properties><titles><title lang="es">CORO 209: BELLAS PALABRAS DE VIDA</title></titles><auhtors><auhtor>Autor Desconocido</auhtor></auhtors><songbooks><songbook entry="209" name="Himnario de coros"/></songbooks><verseOrder>v1 v2</verseOrder></properties><lyrics><verse name="v1" lang="es"><lines>Bellas Palabras de vida, son las de Cristo Jesús, ellas alientan mi</lines><lines>alma dan fortaleza y salud. Bellas palabras de vida, resplandecen en mi ser.</lines><lines>/: Bellas palabras que nunca en la vida</lines></verse><verse name="v2" lang="es"><lines>había escuchado hasta hoy:/</lines></verse></lyrics></song>