<?xml version="1.0" encoding="UTF-8"?><song xmlns="http://openlyrics.info/namespace/2009/song" version="0.8" createdIn="toOpenLyrics"><properties><titles><title lang="es">Hay Un Canto Nuevo</title></titles><auhtors><auhtor>Autor desconocido</auhtor></auhtors><songbooks><songbook entry="21" name="Nuestos Himnos Predilectos"/></songbooks><verseOrder>v1 c1 v2 c1 v3 c1 v4 c1 v5</verseOrder></properties><lyrics><verse name="v1" lang="es"><lines>Hay un canto nuevo en mi ser</lines><lines>es la voz de mi Jesús</lines><lines>que me dice ven a descansar</lines><lines>tu paz conquiste en la cruz</lines></verse><verse name="c1" lang="es"><lines>Cristo, Cristo, Cristo</lines><lines>nombre sin igual</lines><lines>llena siempre mi alma</lines><lines>de esa nota celestial</lines></verse><verse name="v2" lang="es"><lines>Naufrago en pecado me encontré</lines><lines>sin paz en mi corazón</lines><lines>mas en Cristo mi Señor halle</lines><lines>dulce paz y protección</lines></verse><verse name="v3" lang="es"><lines>Tengo de su Gracia celestial</lines><lines>bajo sus alas de amor</lines><lines>riquezas que fluyen a raudal</lines><lines>desde el trono del Señor</lines></verse><verse name="v4" lang="es"><lines>Por las aguan hondas me llevo</lines><lines>pruebas en mi senda halle</lines><lines>por sendero áspero me guio</lines><lines>mas sus huellas seguiré.</lines></verse><verse name="v5" lang="es"><lines>Cristo en las nubes volverá</lines><lines>bajo el bello cielo azul</lines><lines>el entonces mi alma llevara</lines><lines>a vivir en gloria y luz.</lines></verse></lyrics></song>