<?xml version="1.0" encoding="UTF-8"?><song xmlns="http://openlyrics.info/namespace/2009/song" version="0.8" createdIn="toOpenLyrics"><properties><titles><title lang="es">Tras La Tormenta</title></titles><auhtors><auhtor>Autor desconocido</auhtor></auhtors><songbooks><songbook entry="366" name="Nuestos Himnos Predilectos"/></songbooks><verseOrder>v1 c1 v2 c1 v3</verseOrder></properties><lyrics><verse name="v1" lang="es"><lines>Tras la tormenta el arco iris, </lines><lines>y tras la oscuridad, la luz; </lines><lines>tras la amargura, la alegría </lines><lines>que a los creyentes da Jesús.</lines></verse><verse name="c1" lang="es"><lines>Alegre canto mi alma eleva, </lines><lines>pues tras el velo Cristo está; </lines><lines>sostiéneme la fe en su Nombre,</lines><lines>y he de mirar su augusta Faz.</lines></verse><verse name="v2" lang="es"><lines>Tras el invierno, primavera; </lines><lines>tras el combate rudo, paz; </lines><lines>tras triste valle, excelsa cumbre;</lines><lines>tras cautiverio, libertad.</lines></verse><verse name="v3" lang="es"><lines>Tras cuanto vemos, Dios el Padre,</lines><lines>su amor que nunca faltará; </lines><lines>tras este mundo, el cielo, a donde</lines><lines>Jesús nos ha de trasladar.</lines></verse></lyrics></song>