<?xml version="1.0" encoding="UTF-8"?><song xmlns="http://openlyrics.info/namespace/2009/song" version="0.8" createdIn="toOpenLyrics"><properties><titles><title lang="es">Alabarte Hemos</title></titles><auhtors><auhtor>Autor desconocido</auhtor></auhtors><songbooks><songbook entry="82" name="Nuestos Himnos Predilectos"/></songbooks><verseOrder>v1 c1 v2</verseOrder></properties><lyrics><verse name="v1" lang="es"><lines>Alabarte hemos, ¡Oh, Jehová!</lines><lines>Por tu palabra.</lines><lines>Fuente es de todo bien</lines><lines>para tu pueblo.</lines><lines>Recibe alto tributo</lines><lines>que te rendimos hoy,</lines><lines>acepta la alabanza de nuestro corazón.</lines></verse><verse name="c1" lang="es"><lines>Alabarte hemos, alabarte hemos,</lines><lines>alabarte hemos /:por tu bondad:/ y amor.</lines><lines>Es tu Palabra a nuestra boca miel;</lines><lines>Tus Estatutos, vida al corazón;</lines><lines>concédenos libarla hasta el morir</lines><lines>y deleitarnos con tus Dichos hoy.</lines></verse><verse name="v2" lang="es"><lines>Adorarte hemos, ¡oh, Jehová!</lines><lines>Rey de la gloria.</lines><lines>Tu Libro es eternal, Divina historia.</lines><lines>Es fuente inagotable de tu Divino amor,</lines><lines>precioso testimonio de Cristo el Salvador.</lines></verse></lyrics></song>