<?xml version="1.0" encoding="UTF-8"?><song xmlns="http://openlyrics.info/namespace/2009/song" version="0.8" createdIn="toOpenLyrics"><properties><titles><title lang="es">Y De Tal Manera Dios Amó</title></titles><auhtors><auhtor>Autor desconocido</auhtor></auhtors><songbooks><songbook entry="51" name="Nuestos Himnos Predilectos"/></songbooks><verseOrder>v1 v2 v3 v4</verseOrder></properties><lyrics><verse name="v1" lang="es"><lines>Y de tal manera Dios amó al mundo,</lines><lines>que salvarlo quiso de su perdición.</lines><lines>Dando a su Hijo Amado, para que en su Nombre</lines><lines>nadie se perdiera, pues Dios es amor.</lines></verse><verse name="v2" lang="es"><lines>Su Sangre inocente fue la nueva alianza,</lines><lines>que al mundo salvara de muerte y dolor.</lines><lines>Su Doctrina sabia, noble, pura y santa,</lines><lines>hoy enseña al mundo, que Dios es amor</lines></verse><verse name="v3" lang="es"><lines>He aquí el Cordero, que quita el pecado,</lines><lines>del que arrepentido implora el perdón.</lines><lines>y ya redimido, por Jesús salvado,</lines><lines>cantará confiado, que Dios es amor.</lines></verse><verse name="v4" lang="es"><lines>Cerca está el día, en que de lo excelso,</lines><lines>viene manifiesto, con gloria y honor,</lines><lines>Jesucristo, el Verbo, cuando el Universo</lines><lines>por los siglos diga, que Dios es amor.</lines></verse></lyrics></song>