<?xml version="1.0" encoding="UTF-8"?><song xmlns="http://openlyrics.info/namespace/2009/song" version="0.8" createdIn="toOpenLyrics"><properties><titles><title lang="es">Dame, Señor, El Espíritu Divino</title></titles><auhtors><auhtor>Autor desconocido</auhtor></auhtors><songbooks><songbook entry="74" name="Nuestos Himnos Predilectos"/></songbooks><verseOrder>v1 v2 v3 v4</verseOrder></properties><lyrics><verse name="v1" lang="es"><lines>Dame, Señor, el Espíritu Divino,</lines><lines>Dame, Señor este Fuego Celestial.</lines><lines>Llena de luz y victoria mi camino,</lines><lines>Dame, Señor, el Poder Pentecostal.</lines></verse><verse name="v2" lang="es"><lines>Dame, Señor, el Poder que nos inspira;</lines><lines>tu Santa Gracia, que llena de valor.</lines><lines>Oye, Señor, los cantares de mi lira,</lines><lines>que piden hoy Fuego Santo de tu amor .</lines></verse><verse name="v3" lang="es"><lines>Dame, Señor, esa lluvia deliciosa;</lines><lines>lluvia de amor, hoy te pido con fervor .</lines><lines>Cumple hoy en mí tu Verdad maravillosa;</lines><lines>dame, Señor, ese gran Consolador.</lines></verse><verse name="v4" lang="es"><lines>Vengo, Señor, a tus Plantas humillado;</lines><lines>vengo, Señor, con mi férvida oración.</lines><lines>Todo mi ser, sólo a Ti, mi Dios, lo he dado;</lines><lines>dame, Señor, hoy tu fiel contestación.</lines></verse></lyrics></song>