<?xml version="1.0" encoding="UTF-8"?><song xmlns="http://openlyrics.info/namespace/2009/song" version="0.8" createdIn="toOpenLyrics"><properties><titles><title lang="es">NHP 99: CON GOZO SANTO</title></titles><auhtors><auhtor>Autor desconocido</auhtor></auhtors><songbooks><songbook entry="99" name="Nuestos Himnos Predilectos"/></songbooks><verseOrder>v1 c1 v2 c1 v3 c1 v4</verseOrder></properties><lyrics><verse name="v1" lang="es"><lines>Con gozo santo aquí nos congregamos,</lines><lines>con los hermanos que son de este lugar;</lines><lines>pues todos juntos a Cristo alabamos,</lines><lines>y en Su Nombre hemos de prosperar.</lines></verse><verse name="c1" lang="es"><lines>Hermanos, todos estemos con firmeza,</lines><lines>no desmayemos, que vamos a triunfar.</lines><lines>Todo podemos en Cristo y con su fuerza,</lines><lines>y gozaremos en el Reino Celestial.</lines></verse><verse name="v2" lang="es"><lines>Pues nunca temas, pueblo de Jesucristo,</lines><lines>que ni las pruebas te hagan retroceder.</lines><lines>Las maravillas que en todo tiempo has visto,</lines><lines>jamás, jamás las dejarás de ver.</lines></verse><verse name="v3" lang="es"><lines>Mi Jesucristo es Fiel en sus Promesas,</lines><lines>si no le dejas, El no te dejará;</lines><lines>espera siempre en todas sus grandezas,</lines><lines>y bendiciones jamás te faltaran.</lines></verse><verse name="v4" lang="es"><lines>Con la potencia de Su Espíritu Santo,</lines><lines>sentimos gozo en nuestro corazón.</lines><lines>Muy fervorosos sigámonos gozando</lines><lines>hasta llegar al Trono del Señor.</lines></verse></lyrics></song>