<?xml version="1.0" encoding="UTF-8"?><song xmlns="http://openlyrics.info/namespace/2009/song" version="0.8" createdIn="toOpenLyrics"><properties><titles><title lang="es">NHP 5: AL CIELO VUELEN</title></titles><auhtors><auhtor>Autor desconocido</auhtor></auhtors><songbooks><songbook entry="5" name="Nuestos Himnos Predilectos"/></songbooks><verseOrder>v1 c1 v2 c1 v3 c1 v4</verseOrder></properties><lyrics><verse name="v1" lang="es"><lines>Al cielo vuelen los ecos santos,</lines><lines>que arranco alegre de mi laúd;</lines><lines>al cielo vuelen mis dulces cantos,</lines><lines>mis dulces cantos de gratitud.</lines></verse><verse name="c1" lang="es"><lines>¡Alza tu canto, oh, lengua mía!</lines><lines>¡Alza tu canto, mi corazón!</lines><lines>Llénese el alma de alegría,</lines><lines>con alegría de devoción.</lines></verse><verse name="v2" lang="es"><lines>Ya siento el fuego de los amores,</lines><lines>de los amores del grato Edén;</lines><lines>ya no me acosan aquí dolores,</lines><lines>porque contemplo á Jerusalem.</lines></verse><verse name="v3" lang="es"><lines>Padre, en tu regia, santa morada,</lines><lines>donde la dicha no tiene fin:</lines><lines>allí mi Patria miro esmaltada,</lines><lines>de bellas flores de tu jardín.</lines></verse><verse name="v4" lang="es"><lines>¡Oh! Padre, impárteme tu consuelo</lines><lines>nada en la tierra yo espero ya,</lines><lines>y haz que pueda entrar al cielo,</lines><lines>donde tan sólo mi dicha está.</lines></verse></lyrics></song>