{
  "titles": ["¡Oh, Dios, Visítanos!"],
  "authors": ["Autor desconocido"],
  "languages": ["spanish"],
  "songbooks": [{ "name": "Nuestos Himnos Predilectos", "number": "79" }],
  "lyrics": [
    {
      "language": "spanish",
      "order": ["v1", "v2", "v3"],
      "lyric": {
        "v1": [
          "¡Oh, Dios, visítanos, no tardes!",
          "Mándanos, ¡Oh, Señor, tu Poder!",
          "Venimos hoya tus altares,",
          "manifiesta, oh, Señor, tu Poder!",
          "Es tu promesa, Salvador,",
          "darnos el gran Consolador ,",
          "que nos dará mayor fervor;",
          "sí, demuestra ¡Oh, Señor!, tu Poder."
        ],
        "v2": [
          "Dios de Elías, te pedimos,",
          "que reveles hoy tu gran Poder;",
          "que sepa el mundo que servimos",
          "al Dios vivo de Gracia y Poder .",
          "Sí, quítanos toda maldad,",
          "impártenos tu santidad",
          "y guárdanos en libertad,",
          "sí, demuestra ¡Oh, Señor!, tu Poder."
        ],
        "v3": [
          "Avívanos, Señor, escucha,",
          "manifiesta, ¡Oh, Señor!, tu Poder.",
          "El ánimo y fe levanta,",
          "ejercita ¡Oh, Señor!, tu Poder.",
          "Inflama nuestro corazón,",
          "concédenos más compasión,",
          "gocemos dulce comunión,",
          "sí, demuestra ¡Oh, Señor!, tu Poder."
        ]
      }
    }
  ],
  "versions": []
}
